odoo/addons/resource_booking/README.rst
odoo/addons/resource_booking/__init__.py
odoo/addons/resource_booking/__manifest__.py
odoo/addons/resource_booking/controllers/__init__.py
odoo/addons/resource_booking/controllers/portal.py
odoo/addons/resource_booking/data/mail.xml
odoo/addons/resource_booking/demo/res_users_demo.xml
odoo/addons/resource_booking/i18n/da.po
odoo/addons/resource_booking/i18n/es.po
odoo/addons/resource_booking/i18n/fr.po
odoo/addons/resource_booking/i18n/fr_CH.po
odoo/addons/resource_booking/i18n/fr_FR.po
odoo/addons/resource_booking/i18n/resource_booking.pot
odoo/addons/resource_booking/models/__init__.py
odoo/addons/resource_booking/models/calendar_event.py
odoo/addons/resource_booking/models/resource_booking.py
odoo/addons/resource_booking/models/resource_booking_combination.py
odoo/addons/resource_booking/models/resource_booking_type.py
odoo/addons/resource_booking/models/resource_booking_type_combination_rel.py
odoo/addons/resource_booking/models/resource_calendar.py
odoo/addons/resource_booking/models/resource_resource.py
odoo/addons/resource_booking/readme/CONFIGURE.rst
odoo/addons/resource_booking/readme/CONTRIBUTORS.rst
odoo/addons/resource_booking/readme/DESCRIPTION.rst
odoo/addons/resource_booking/readme/INSTALL.rst
odoo/addons/resource_booking/readme/ROADMAP.rst
odoo/addons/resource_booking/readme/USAGE.rst
odoo/addons/resource_booking/security/ir.model.access.csv
odoo/addons/resource_booking/security/resource_booking_security.xml
odoo/addons/resource_booking/static/description/icon.png
odoo/addons/resource_booking/static/description/icon.svg
odoo/addons/resource_booking/static/description/index.html
odoo/addons/resource_booking/static/src/css/portal.scss
odoo/addons/resource_booking/templates/assets.xml
odoo/addons/resource_booking/templates/portal.xml
odoo/addons/resource_booking/tests/__init__.py
odoo/addons/resource_booking/tests/common.py
odoo/addons/resource_booking/tests/test_backend.py
odoo12_addon_resource_booking-12.0.1.5.1.dist-info/METADATA
odoo12_addon_resource_booking-12.0.1.5.1.dist-info/WHEEL
odoo12_addon_resource_booking-12.0.1.5.1.dist-info/top_level.txt
odoo12_addon_resource_booking-12.0.1.5.1.dist-info/RECORD
