Metadata-Version: 2.1
Name: odoo12-addon-resource-booking
Version: 12.0.1.5.1
Summary: Manage appointments and resource booking
Home-page: https://github.com/OCA/calendar
Author: Tecnativa, Odoo Community Association (OCA)
Author-email: support@odoo-community.org
License: AGPL-3
Platform: UNKNOWN
Classifier: Programming Language :: Python
Classifier: Framework :: Odoo
Classifier: Framework :: Odoo :: 12.0
Classifier: License :: OSI Approved :: GNU Affero General Public License v3
Classifier: Development Status :: 4 - Beta
Requires-Python: >=3.5
Requires-Dist: cssselect
Requires-Dist: freezegun
Requires-Dist: odoo12-addon-web-calendar-slot-duration
Requires-Dist: odoo (<12.1dev,>=12.0a)
